{
  "version": "7",
  "dialect": "postgresql",
  "entries": [
    {
      "idx": 0,
      "version": "7",
      "when": 1739728839708,
      "tag": "0000_red_microchip",
      "breakpoints": true
    },
    {
      "idx": 1,
      "version": "7",
      "when": 1740450309990,
      "tag": "0001_powerful_lila_cheney",
      "breakpoints": true
    },
    {
      "idx": 2,
      "version": "7",
      "when": 1740528772266,
      "tag": "0002_flimsy_miracleman",
      "breakpoints": true
    },
    {
      "idx": 3,
      "version": "7",
      "when": 1743034027717,
      "tag": "0003_flashy_diamondback",
      "breakpoints": true
    }
  ]
}